README.txt
setup.py
bin/sparql11-server.py
sparql11/QueryHandler.py
sparql11/SPARQLEndpoint.py
sparql11/__init__.py
sparql11/server.py
sparql11.egg-info/PKG-INFO
sparql11.egg-info/SOURCES.txt
sparql11.egg-info/dependency_links.txt
sparql11.egg-info/top_level.txt