Metadata-Version: 1.0
Name: sparql11
Version: 0.0.1
Summary: SPARQL1.1 protocol compliant endpoint
Home-page: http://scharrenbach.net
Author: Thomas Scharrenbach
Author-email: thomas@scharrenbach.net
License: LICENSE.txt
Platform: UNKNOWN
